debate_hall_mcp/__init__.py
debate_hall_mcp/engine.py
debate_hall_mcp/github.py
debate_hall_mcp/octave_formatter.py
debate_hall_mcp/server.py
debate_hall_mcp/state.py
debate_hall_mcp/validation.py
debate_hall_mcp/prompts/__init__.py
debate_hall_mcp/tools/__init__.py
debate_hall_mcp/tools/admin.py
debate_hall_mcp/tools/close.py
debate_hall_mcp/tools/get.py
debate_hall_mcp/tools/github_sync.py
debate_hall_mcp/tools/init.py
debate_hall_mcp/tools/interject.py
debate_hall_mcp/tools/pick.py
debate_hall_mcp/tools/ratify.py
debate_hall_mcp/tools/turn.py
debate_hall_mcp/utils/__init__.py
debate_hall_mcp/utils/env.py
debate_hall_mcp-0.4.0.dist-info/METADATA
debate_hall_mcp-0.4.0.dist-info/WHEEL
debate_hall_mcp-0.4.0.dist-info/entry_points.txt
debate_hall_mcp-0.4.0.dist-info/licenses/LICENSE
debate_hall_mcp-0.4.0.dist-info/RECORD
