Metadata-Version: 2.4
Name: debate-hall-mcp
Version: 0.4.0
Summary: Production-grade MCP server for Wind/Wall/Door multi-perspective debate orchestration
Project-URL: Homepage, https://github.com/elevanaltd/debate-hall-mcp
Project-URL: Documentation, https://github.com/elevanaltd/debate-hall-mcp#readme
Project-URL: Repository, https://github.com/elevanaltd/debate-hall-mcp.git
Project-URL: Issues, https://github.com/elevanaltd/debate-hall-mcp/issues
Author-email: HestAI <dev@hestai.com>
License: Apache-2.0
License-File: LICENSE
Keywords: ai,debate,ethos,logos,mcp,orchestration,pathos,wind-wall-door
Classifier: Development Status :: 4 - Beta
Classifier: Intended Audience :: Developers
Classifier: License :: OSI Approved :: Apache Software License
Classifier: Programming Language :: Python :: 3
Classifier: Programming Language :: Python :: 3.11
Classifier: Programming Language :: Python :: 3.12
Classifier: Topic :: Scientific/Engineering :: Artificial Intelligence
Requires-Python: >=3.11
Requires-Dist: filelock>=3.0.0
Requires-Dist: httpx>=0.27.0
Requires-Dist: mcp>=1.0.0
Requires-Dist: octave-mcp>=0.6.1
Requires-Dist: pydantic>=2.0.0
Requires-Dist: python-dotenv>=1.0.0
Provides-Extra: dev
Requires-Dist: black>=24.0.0; extra == 'dev'
Requires-Dist: inline-snapshot>=0.15.0; extra == 'dev'
Requires-Dist: mypy>=1.13.0; extra == 'dev'
Requires-Dist: pytest-asyncio>=0.24.0; extra == 'dev'
Requires-Dist: pytest-cov>=4.1.0; extra == 'dev'
Requires-Dist: pytest>=8.0.0; extra == 'dev'
Requires-Dist: ruff>=0.8.0; extra == 'dev'
